singhtools/__init__.py
singhtools/singhtools.py
singhtools-0.1.2a0.dist-info/LICENSE
singhtools-0.1.2a0.dist-info/METADATA
singhtools-0.1.2a0.dist-info/WHEEL
singhtools-0.1.2a0.dist-info/top_level.txt
singhtools-0.1.2a0.dist-info/RECORD
