Metadata-Version: 2.1
Name: singhtools
Version: 0.1.2a0
Summary: Functions for estimating coverage of confidence structures
Home-page: https://github.com/Institute-for-Risk-and-Uncertainty/Singh-Tools
Author: Alexander Wimbush
Author-email: alexanderpwimbush@gmail.com
License: gpl-3.0
Download-URL: https://github.com/Institute-for-Risk-and-Uncertainty/Singh-Tools/archive/0.1.12-alpha.tar.gz
Keywords: confidence
Platform: UNKNOWN
Requires-Dist: numpy
